cj_crawling/__init__.py
cj_crawling/koofs.py
cj_crawling-0.1.dist-info/METADATA
cj_crawling-0.1.dist-info/WHEEL
cj_crawling-0.1.dist-info/top_level.txt
cj_crawling-0.1.dist-info/RECORD
