Metadata-Version: 2.1
Name: cj-crawling
Version: 0.1
Summary: cj_crawling
Home-page: https://github.com/qkdrk7777775/cj_crawling
Author: changje.cho
Author-email: qkdrk7777775@gmail.com
License: UNKNOWN
Download-URL: https://github.com/qkdrk7777775/cj_crawlingj/archive/master.zip
Keywords: khoa
Platform: UNKNOWN
Classifier: Programming Language :: Python :: 3
Classifier: Programming Language :: Python :: 3.2
Classifier: Programming Language :: Python :: 3.3
Classifier: Programming Language :: Python :: 3.4
Classifier: Programming Language :: Python :: 3.5
Classifier: Programming Language :: Python :: 3.6
Classifier: Programming Language :: Python :: 3.7
Requires-Python: >=3
